tma_authenticator/__init__.py
tma_authenticator/security_provider.py
tma_authenticator/service_auth.py
tma_authenticator/storage_provider.py
tma_authenticator/tma_authentication_router.py
tma_authenticator/tma_authenticator.py
tma_authenticator/token.py
tma_authenticator/ton_authorization.py
tma_authenticator/users.py
tma_authenticator/web3_ton_router.py
tma_authenticator-2.1.0.dist-info/METADATA
tma_authenticator-2.1.0.dist-info/WHEEL
tma_authenticator-2.1.0.dist-info/RECORD
