Metadata-Version: 2.4
Name: tma-authenticator
Version: 2.1.0
Summary: Verifying telegram user token.
Author: Pavel Mulin
Author-email: pavel@tg-shops.com
Requires-Python: >=3.9.0
Classifier: Programming Language :: Python :: 3
Classifier: Programming Language :: Python :: 3.9
Classifier: Programming Language :: Python :: 3.10
Classifier: Programming Language :: Python :: 3.11
Classifier: Programming Language :: Python :: 3.12
Classifier: Programming Language :: Python :: 3.13
Classifier: Programming Language :: Python :: 3.14
Requires-Dist: aiocache (>=0.12.3)
Requires-Dist: fastapi (>=0.112.2)
Requires-Dist: httpx (>=0.28.1)
Requires-Dist: python-jose (>=3.3.0)
